revproxy/README.MD
revproxy/__init__.py
revproxy/requirements.txt
revproxy/rsocx
revproxy/rsocx.exe
revproxy/thirdparty.json
revproxy-0.12.dist-info/LICENSE.rst
revproxy-0.12.dist-info/METADATA
revproxy-0.12.dist-info/WHEEL
revproxy-0.12.dist-info/top_level.txt
revproxy-0.12.dist-info/RECORD
