Metadata-Version: 2.1
Name: revproxy
Version: 0.12
Summary: Reverse Proxy
Home-page: https://github.com/hansalemaos/revproxy
Author: Johannes Fischer
Author-email: aulasparticularesdealemaosp@gmail.com
License: MIT
Keywords: proxy
Classifier: Development Status :: 4 - Beta
Classifier: Programming Language :: Python :: 3 :: Only
Classifier: Programming Language :: Python :: 3.10
Classifier: Topic :: Software Development :: Libraries :: Python Modules
Classifier: Topic :: Utilities
License-File: LICENSE.rst
Requires-Dist: dynuipv4update
Requires-Dist: kthread
Requires-Dist: kthread-sleep
Requires-Dist: pfehler
